{
	"info": {
		"_postman_id": "3eea09a4-1147-4bd5-9ffd-a344291f4422",
		"name": "leadResponse",
		"schema": "https://schema.getpostman.com/json/collection/v2.1.0/collection.json"
	},
	"item": [
		{
			"name": "deleteLeadResponse",
			"request": {
				"auth": {
					"type": "bearer",
					"bearer": [
						{
							"key": "token",
							"value": "{{jwt}}",
							"type": "string"
						}
					]
				},
				"method": "DELETE",
				"header": [],
				"url": {
					"raw": "{{URL}}/api/v1/lead-response/5faa9ca3152e242dbc43d02f",
					"host": [
						"{{URL}}"
					],
					"path": [
						"api",
						"v1",
						"lead-response",
						"5faa9ca3152e242dbc43d02f"
					]
				}
			},
			"response": []
		},
		{
			"name": "getLeadResponse",
			"request": {
				"auth": {
					"type": "bearer",
					"bearer": [
						{
							"key": "token",
							"value": "{{jwt}}",
							"type": "string"
						}
					]
				},
				"method": "GET",
				"header": [],
				"url": {
					"raw": "{{URL}}/api/v1/lead-response/5faa9ca3152e242dbc43d02f",
					"host": [
						"{{URL}}"
					],
					"path": [
						"api",
						"v1",
						"lead-response",
						"5faa9ca3152e242dbc43d02f"
					]
				}
			},
			"response": []
		},
		{
			"name": "getAllLeadResponse",
			"request": {
				"auth": {
					"type": "bearer",
					"bearer": [
						{
							"key": "token",
							"value": "{{jwt}}",
							"type": "string"
						}
					]
				},
				"method": "GET",
				"header": [],
				"url": {
					"raw": "{{URL}}/api/v1/lead-response/",
					"host": [
						"{{URL}}"
					],
					"path": [
						"api",
						"v1",
						"lead-response",
						""
					]
				}
			},
			"response": []
		},
		{
			"name": "updateLeadResponse",
			"request": {
				"auth": {
					"type": "bearer",
					"bearer": [
						{
							"key": "token",
							"value": "{{jwt}}",
							"type": "string"
						}
					]
				},
				"method": "PATCH",
				"header": [],
				"body": {
					"mode": "raw",
					"raw": "{\r\n  \"_leadId\":\"5f9d4cad0cc36e2a44c325b9\",\r\n  \"_responderId\":\"5f9d4cad0cc36e2a44c325b9\",\r\n  \"emailSent\":true,\r\n  \"isStatusChange\":false,\r\n  \"message\":\"Hello\",\r\n  \"status\":\"Done\"\r\n}",
					"options": {
						"raw": {
							"language": "json"
						}
					}
				},
				"url": {
					"raw": "{{URL}}/api/v1/lead-response/5faa9ca3152e242dbc43d02f",
					"host": [
						"{{URL}}"
					],
					"path": [
						"api",
						"v1",
						"lead-response",
						"5faa9ca3152e242dbc43d02f"
					]
				}
			},
			"response": []
		},
		{
			"name": "createLeadResponse",
			"request": {
				"auth": {
					"type": "bearer",
					"bearer": [
						{
							"key": "token",
							"value": "{{jwt}}",
							"type": "string"
						}
					]
				},
				"method": "POST",
				"header": [],
				"body": {
					"mode": "raw",
					"raw": "{\r\n  \"_leadId\":\"5f9d4cad0cc36e2a44c325b9\",\r\n  \"_responderId\":\"5f9d4cad0cc36e2a44c325b9\",\r\n  \"emailSent\":false,\r\n  \"isStatusChange\":false,\r\n  \"message\":\"Hello\",\r\n  \"status\":\"Done\"\r\n}",
					"options": {
						"raw": {
							"language": "json"
						}
					}
				},
				"url": {
					"raw": "{{URL}}/api/v1/lead-response/",
					"host": [
						"{{URL}}"
					],
					"path": [
						"api",
						"v1",
						"lead-response",
						""
					]
				}
			},
			"response": []
		}
	],
	"protocolProfileBehavior": {}
}