{
	"info": {
		"_postman_id": "140f9de5-7956-4240-b2a5-daa7dc801379",
		"name": "ratingAttribute",
		"schema": "https://schema.getpostman.com/json/collection/v2.1.0/collection.json"
	},
	"item": [
		{
			"name": "getAllRatingAttribute",
			"request": {
				"method": "GET",
				"header": [],
				"url": {
					"raw": "localhost:3000/api/v1/ratingAttribute",
					"host": [
						"localhost"
					],
					"port": "3000",
					"path": [
						"api",
						"v1",
						"ratingAttribute"
					]
				}
			},
			"response": []
		},
		{
			"name": "createRatingAttribute",
			"request": {
				"method": "POST",
				"header": [],
				"body": {
					"mode": "raw",
					"raw": "{\r\n  \"Name\": \"viky\",\r\n  \"type\": \"sudent\",\r\n  \"Description\": \"college student\",\r\n  \"Notes\": \"english\",\r\n  \"status\": \"high\"\r\n}",
					"options": {
						"raw": {
							"language": "json"
						}
					}
				},
				"url": {
					"raw": "localhost:3000/api/v1/ratingAttribute",
					"host": [
						"localhost"
					],
					"port": "3000",
					"path": [
						"api",
						"v1",
						"ratingAttribute"
					]
				}
			},
			"response": []
		},
		{
			"name": "getRatingAttribute",
			"request": {
				"method": "GET",
				"header": [],
				"url": {
					"raw": "localhost:3000/api/v1/ratingAttribute/5f990bb3c727e952a076f3b7",
					"host": [
						"localhost"
					],
					"port": "3000",
					"path": [
						"api",
						"v1",
						"ratingAttribute",
						"5f990bb3c727e952a076f3b7"
					]
				}
			},
			"response": []
		},
		{
			"name": "updateRatingAttribute",
			"request": {
				"method": "PATCH",
				"header": [],
				"body": {
					"mode": "raw",
					"raw": "{\r\n  \"Name\": \"viky\",\r\n  \"type\": \"sudent\",\r\n  \"Description\": \"college student\",\r\n  \"Notes\": \"english\",\r\n  \"status\": \"high\"\r\n}",
					"options": {
						"raw": {
							"language": "json"
						}
					}
				},
				"url": {
					"raw": "localhost:3000/api/v1/ratingAttribute/5f990bb3c727e952a076f3b7",
					"host": [
						"localhost"
					],
					"port": "3000",
					"path": [
						"api",
						"v1",
						"ratingAttribute",
						"5f990bb3c727e952a076f3b7"
					]
				}
			},
			"response": []
		},
		{
			"name": "deleteRatingAttribute",
			"request": {
				"method": "DELETE",
				"header": [],
				"url": {
					"raw": "localhost:3000/api/v1/ratingAttribute/5f990bb3c727e952a076f3b7",
					"host": [
						"localhost"
					],
					"port": "3000",
					"path": [
						"api",
						"v1",
						"ratingAttribute",
						"5f990bb3c727e952a076f3b7"
					]
				}
			},
			"response": []
		}
	],
	"protocolProfileBehavior": {}
}